shell_ai/__init__.py
shell_ai/code_parser.py
shell_ai/config.py
shell_ai/main.py
shell_ai/parallel_suggestions.py
shell_ai-0.4.4.dist-info/licenses/LICENSE
shell_ai-0.4.4.dist-info/METADATA
shell_ai-0.4.4.dist-info/WHEEL
shell_ai-0.4.4.dist-info/entry_points.txt
shell_ai-0.4.4.dist-info/top_level.txt
shell_ai-0.4.4.dist-info/RECORD
