Metadata-Version: 2.4
Name: shell-ai
Version: 0.4.4
Author: Rick Lamers
License-File: LICENSE
Requires-Dist: langchain~=0.3.0
Requires-Dist: langchain-openai~=0.2.0
Requires-Dist: openai~=1.57.0
Requires-Dist: InquirerPy~=0.3.0
Requires-Dist: mistune~=3.0.0
Requires-Dist: groq~=0.13.0
Requires-Dist: langchain-groq~=0.2.0
Requires-Dist: langchain-mistralai==0.2.11
Provides-Extra: dev
Requires-Dist: setuptools; extra == "dev"
Requires-Dist: wheel; extra == "dev"
Requires-Dist: twine; extra == "dev"
Dynamic: author
Dynamic: description
Dynamic: description-content-type
Dynamic: license-file
Dynamic: provides-extra
Dynamic: requires-dist
